MANIFEST.in
README.rst
setup.py
configs/apache_access.yml
configs/aptitude.yml
configs/ls.yml
configs/pysetup.yml
docs/INSTALL.rst
docs/README.rst
docs/conf.py
docs/index.rst
docs/screenshots/apache_access_after.png
docs/screenshots/apache_access_before.png
docs/screenshots/aptitude_after.png
docs/screenshots/aptitude_before.png
docs/screenshots/pysetup_after.png
docs/screenshots/pysetup_before.png
strec/__init__.py
strec/core.py
strec/version.py
strec.egg-info/PKG-INFO
strec.egg-info/SOURCES.txt
strec.egg-info/dependency_links.txt
strec.egg-info/entry_points.txt
strec.egg-info/not-zip-safe
strec.egg-info/requires.txt
strec.egg-info/top_level.txt