Metadata-Version: 2.1
Name: strec
Version: 1.0.0.post2
Summary: Generic Coloriser
Home-page: UNKNOWN
Author: Michel Albert
Author-email: michel@albert.lu
License: GPL
Platform: UNKNOWN
Provides-Extra: test
